{"966c3a279e18743d09b38b7abaf916ca:98eeb5baeb57b9a25ad1b8f99a31d1fc":{"statistic":{"failed":0,"broken":0,"skipped":0,"passed":1,"unknown":0,"total":1},"items":[{"uid":"2b988ecae298f2f3","reportUrl":"https://nurulsilpia.github.io/playwright_API_Practice/3//#testresult/2b988ecae298f2f3","status":"passed","time":{"start":1692354980528,"stop":1692354980854,"duration":326}}]},"6e33a0a1c366e1abd8eee72ec3ee0d27:0f9e057ca0d46c7277d7e42f0907a88c":{"statistic":{"failed":0,"broken":0,"skipped":0,"passed":1,"unknown":0,"total":1},"items":[{"uid":"1aed0d6e8c1911c4","reportUrl":"https://nurulsilpia.github.io/playwright_API_Practice/3//#testresult/1aed0d6e8c1911c4","status":"passed","time":{"start":1692354981396,"stop":1692354981560,"duration":164}}]},"dd74274dcbb2205637f4918d725ea701:6ff12be410e71a97d1a275b125c047ef":{"statistic":{"failed":0,"broken":0,"skipped":0,"passed":1,"unknown":0,"total":1},"items":[{"uid":"b58fbfb8569d06a1","reportUrl":"https://nurulsilpia.github.io/playwright_API_Practice/3//#testresult/b58fbfb8569d06a1","status":"passed","time":{"start":1692354981560,"stop":1692354981727,"duration":167}}]},"385b48bcad0454e7fb2c85ac20eea5be:e07a33bbe390e8bd0e50e48dfadd19f3":{"statistic":{"failed":0,"broken":0,"skipped":0,"passed":1,"unknown":0,"total":1},"items":[{"uid":"81a843324effdfe2","reportUrl":"https://nurulsilpia.github.io/playwright_API_Practice/3//#testresult/81a843324effdfe2","status":"passed","time":{"start":1692354981149,"stop":1692354981395,"duration":246}}]},"780a66d21c0b5038db7a54ae5600e687:e9532053c740491a51e77418def01dd2":{"statistic":{"failed":0,"broken":0,"skipped":0,"passed":1,"unknown":0,"total":1},"items":[{"uid":"245edd20861d9655","reportUrl":"https://nurulsilpia.github.io/playwright_API_Practice/3//#testresult/245edd20861d9655","status":"passed","time":{"start":1692354980854,"stop":1692354981149,"duration":295}}]}}